astra/__init__.py
astra/embedded/__init__.py
astra/embedded/agent.py
astra/server/__init__.py
astra/server/app.py
astra/server/config.py
astra/server/lifecycle.py
astra/server/registry.py
astra/server/auth/__init__.py
astra/server/auth/middleware.py
astra/server/auth/routes.py
astra/server/playground-dist/index.html
astra/server/playground-dist/assets/index-CbrPrM8N.js
astra/server/playground-dist/assets/index-nLkgYpcv.css
astra/server/routes/__init__.py
astra/server/routes/agents.py
astra/server/routes/meta.py
astra/server/routes/threads.py
astra/server/routes/playground/__init__.py
astra/server/routes/playground/agents.py
astra/server/routes/playground/router.py
astra/server/routes/playground/threads.py
astra/server/routes/playground/tools.py
astra_runtime-0.1.5.dist-info/METADATA
astra_runtime-0.1.5.dist-info/WHEEL
astra_runtime-0.1.5.dist-info/licenses/LICENSE
astra_runtime-0.1.5.dist-info/RECORD
