Metadata-Version: 2.4
Name: astra-runtime
Version: 0.1.5
Summary: Astra Runtime - Build AI agents, teams, and RAG pipelines in Python with embedded runtime and FastAPI server
Project-URL: Homepage, https://github.com/HeeManSu/astra-agi
Project-URL: Documentation, https://github.com/HeeManSu/astra-agi#readme
Project-URL: Repository, https://github.com/HeeManSu/astra-agi
Project-URL: Issues, https://github.com/HeeManSu/astra-agi/issues
Project-URL: Changelog, https://github.com/HeeManSu/astra-agi/releases
Author-email: Himanshu Sharma <himanshu.kumarr07@gmail.com>
License: MIT
License-File: LICENSE
Keywords: agents,ai,ai-agents,fastapi,framework,langchain-alternative,llm,rag,retrieval-augmented-generation
Classifier: Development Status :: 4 - Beta
Classifier: Framework :: FastAPI
Classifier: Intended Audience :: Developers
Classifier: License :: OSI Approved :: MIT License
Classifier: Programming Language :: Python :: 3
Classifier: Programming Language :: Python :: 3.10
Classifier: Programming Language :: Python :: 3.11
Classifier: Programming Language :: Python :: 3.12
Classifier: Programming Language :: Python :: 3.13
Classifier: Topic :: Scientific/Engineering :: Artificial Intelligence
Classifier: Typing :: Typed
Requires-Python: <3.14,>=3.10
Requires-Dist: astra-framework>=0.1.1
Requires-Dist: bcrypt>=4.0.0
Requires-Dist: email-validator>=2.0.0
Requires-Dist: fastapi>=0.109.0
Requires-Dist: pyjwt>=2.8.0
Requires-Dist: sse-starlette>=2.0.0
Requires-Dist: uvicorn[standard]>=0.27.0
Provides-Extra: all
Requires-Dist: aioboto3>=12.0.0; extra == 'all'
Requires-Dist: beanie>=1.24.0; extra == 'all'
Requires-Dist: boto3>=1.35.0; extra == 'all'
Requires-Dist: motor>=3.3.0; extra == 'all'
Provides-Extra: aws
Requires-Dist: aioboto3>=12.0.0; extra == 'aws'
Requires-Dist: boto3>=1.35.0; extra == 'aws'
Provides-Extra: mongodb
Requires-Dist: beanie>=1.24.0; extra == 'mongodb'
Requires-Dist: motor>=3.3.0; extra == 'mongodb'
Provides-Extra: test
Requires-Dist: httpx>=0.26.0; extra == 'test'
Requires-Dist: pytest-asyncio>=0.23.0; extra == 'test'
Requires-Dist: pytest-cov>=4.0.0; extra == 'test'
Requires-Dist: pytest-xdist>=3.5.0; extra == 'test'
Requires-Dist: pytest>=8.0.0; extra == 'test'
